cosinnus_todo/__init__.py
cosinnus_todo/admin.py
cosinnus_todo/apps.py
cosinnus_todo/conf.py
cosinnus_todo/cosinnus_app.py
cosinnus_todo/cosinnus_notifications.py
cosinnus_todo/dashboard.py
cosinnus_todo/filters.py
cosinnus_todo/forms.py
cosinnus_todo/managers.py
cosinnus_todo/models.py
cosinnus_todo/notify.py
cosinnus_todo/search_indexes.py
cosinnus_todo/serializers.py
cosinnus_todo/urls.py
cosinnus_todo/views.py
cosinnus_todo/locale/de/LC_MESSAGES/django.mo
cosinnus_todo/locale/de/LC_MESSAGES/django.po
cosinnus_todo/locale/en/LC_MESSAGES/django.mo
cosinnus_todo/locale/en/LC_MESSAGES/django.po
cosinnus_todo/locale/fr/LC_MESSAGES/django.mo
cosinnus_todo/locale/fr/LC_MESSAGES/django.po
cosinnus_todo/locale/ru/LC_MESSAGES/django.mo
cosinnus_todo/locale/ru/LC_MESSAGES/django.po
cosinnus_todo/locale/uk/LC_MESSAGES/django.mo
cosinnus_todo/locale/uk/LC_MESSAGES/django.po
cosinnus_todo/migrations/0001_initial.py
cosinnus_todo/migrations/0002_auto_20151104_1711.py
cosinnus_todo/migrations/0003_auto_20160125_1339.py
cosinnus_todo/migrations/__init__.py
cosinnus_todo/static/css/cosinnus_todo/cosinnus_todo.css
cosinnus_todo/templates/cosinnus_todo/attached_object_select_pill.html
cosinnus_todo/templates/cosinnus_todo/attached_todos.html
cosinnus_todo/templates/cosinnus_todo/base.html
cosinnus_todo/templates/cosinnus_todo/leftnav_todoentry.html
cosinnus_todo/templates/cosinnus_todo/single_todo.html
cosinnus_todo/templates/cosinnus_todo/single_todo_detailed.html
cosinnus_todo/templates/cosinnus_todo/todo_comments.html
cosinnus_todo/templates/cosinnus_todo/todo_detail.html
cosinnus_todo/templates/cosinnus_todo/todo_list.html
cosinnus_todo/templates/cosinnus_todo/todoentry_form.html
cosinnus_todo/templates/cosinnus_todo/todolist_form.html
cosinnus_todo/templates/cosinnus_todo/notifications/assigned_to_me.txt
cosinnus_todo/templates/cosinnus_todo/notifications/assigned_to_me_subject.txt
cosinnus_todo-0.6.dev20180515152742.dist-info/DESCRIPTION.rst
cosinnus_todo-0.6.dev20180515152742.dist-info/METADATA
cosinnus_todo-0.6.dev20180515152742.dist-info/RECORD
cosinnus_todo-0.6.dev20180515152742.dist-info/WHEEL
cosinnus_todo-0.6.dev20180515152742.dist-info/metadata.json
cosinnus_todo-0.6.dev20180515152742.dist-info/top_level.txt
